GeneMaster/__init__.py
GeneMaster/main.py
GeneMaster/dtypes/DNA.py
GeneMaster/dtypes/RNA.py
GeneMaster/dtypes/__init__.py
GeneMaster/operations/DNAOperations.py
GeneMaster/operations/RNAOperations.py
GeneMaster/operations/__init__.py
GeneMaster/parsing/__init__.py
GeneMaster/parsing/fasta.py
GeneMaster/tests/__init__.py
GeneMaster/tests/test_dna.py
GeneMaster-1.0.1.dist-info/LICENSE
GeneMaster-1.0.1.dist-info/METADATA
GeneMaster-1.0.1.dist-info/WHEEL
GeneMaster-1.0.1.dist-info/top_level.txt
GeneMaster-1.0.1.dist-info/RECORD
