Metadata-Version: 2.1
Name: GeneMaster
Version: 1.0.1
Summary: A comprehensive package for DNA, RNA, and protein sequence analysis and visualization.
Home-page: https://github.com/AhmedOs13/GeneMaster
Author: Ahmed Osama Taha
Author-email: ahmedosamaofficial13@gmail.com
Classifier: Programming Language :: Python :: 3
Classifier: License :: OSI Approved :: MIT License
Classifier: Operating System :: OS Independent
Classifier: Intended Audience :: Science/Research
Classifier: Topic :: Scientific/Engineering :: Bio-Informatics
Classifier: Topic :: Software Development :: Libraries :: Python Modules
License-File: LICENSE
Requires-Dist: numpy
